lib/__init__.py
lib/myfunctions.py
lib/newsol.py
lib/extra/__init__.py
lib/extra/approx.py
lib/extra/ders.py
lib_4231/__init__.py
lib_4231/newsol.py
lib_4231/extra/__init__.py
lib_4231/extra/approx.py
lib_4231/extra/ders.py
tests/__init__.py
tests/test_myfunctions.py
lib_4231-0.0.1.dist-info/METADATA
lib_4231-0.0.1.dist-info/WHEEL
lib_4231-0.0.1.dist-info/top_level.txt
lib_4231-0.0.1.dist-info/RECORD
