Metadata-Version: 2.1
Name: lib-4231
Version: 0.0.1
Summary: A test Python package
Home-page: UNKNOWN
Author: JP
License: UNKNOWN
Platform: UNKNOWN
Requires-Dist: scipy
